{
  "generated_at": "2026-06-02T18:04:37+00:00",
  "sources": [
    {
      "id": "pred-arbitrage",
      "name": "Pred Arbitrage Scanner",
      "ok": true,
      "updated_at": "2026-06-02T17:04:05.668696+00:00",
      "total": 275,
      "guaranteed_kept": 22
    },
    {
      "id": "polling-agg-2026",
      "name": "Polling Agg 2026 Arb Scanner",
      "ok": true,
      "updated_at": "2026-06-02T16:47:13.468509+00:00",
      "total": 361,
      "guaranteed_kept": 0
    }
  ],
  "arbs": [
    {
      "source": "pred-arbitrage",
      "category": "Elections",
      "label": "",
      "platform_a": "kalshi",
      "platform_b": "polymarket",
      "question_a": "Who will win the 2026 Seoul mayoral election? \u2014 Oh Se-hoon",
      "question_b": "Will Oh Se-hoon win the 2026 Seoul Mayoral Election by between 3% and 6%?",
      "url_a": "https://kalshi.com/markets/KXSEOULMAYOR",
      "url_b": "https://polymarket.com/event/2026-seoul-mayoral-election-margin-of-victory",
      "market_id_a": "KXSEOULMAYOR-26JUN03-OSEH",
      "market_id_b": "58906308086368910647083473848776718874453245913174905797034217604429130073217",
      "prob_a": 0.225,
      "prob_b": 0.0515,
      "stake_a": 6.23,
      "stake_b": 93.77,
      "return_pct": 11.35,
      "settle_date": "2027-06-03",
      "volume_a": 81177.26,
      "volume_b": 4841.69,
      "suspicious": false,
      "suspicion_reasons": []
    },
    {
      "source": "pred-arbitrage",
      "category": "Politics",
      "label": "",
      "platform_a": "kalshi",
      "platform_b": "polymarket",
      "question_a": "Who will be arrested before 2027? \u2014 Jos\u00e9 Luis Rodr\u00edguez Zapatero",
      "question_b": "Will Jos\u00e9 Luis Rodr\u00edguez Zapatero be arrested before 2027?",
      "url_a": "https://kalshi.com/markets/KXARREST",
      "url_b": "https://polymarket.com/event/who-will-be-arrested-before-2027",
      "market_id_a": "KXARREST-27JAN-JZAP",
      "market_id_b": "9748918111047171291668915428928220741057051517923697241459807635775222131283",
      "prob_a": 0.265,
      "prob_b": 0.43,
      "stake_a": 68.26,
      "stake_b": 31.74,
      "return_pct": 10.5,
      "settle_date": "2027-01-01",
      "volume_a": 7192.0,
      "volume_b": 7638.47,
      "suspicious": false,
      "suspicion_reasons": []
    },
    {
      "source": "pred-arbitrage",
      "category": "Entertainment",
      "label": "",
      "platform_a": "kalshi",
      "platform_b": "polymarket",
      "question_a": "TIME's Person of the Year for 2026? \u2014 Benjamin Netanyahu",
      "question_b": "Will Benjamin Netanyahu be TIME Person of the Year 2026?",
      "url_a": "https://kalshi.com/markets/KXTIME",
      "url_b": "https://polymarket.com/event/time-person-of-the-year-2026",
      "market_id_a": "KXTIME-26-BEN",
      "market_id_b": "48890278103385800732996201585531776980950532146938749653275126997915869764317",
      "prob_a": 0.045,
      "prob_b": 0.17,
      "stake_a": 94.86,
      "stake_b": 5.14,
      "return_pct": 6.5,
      "settle_date": "2027-01-01",
      "volume_a": 195.44,
      "volume_b": 1.04,
      "suspicious": false,
      "suspicion_reasons": []
    },
    {
      "source": "pred-arbitrage",
      "category": "Politics",
      "label": "",
      "platform_a": "kalshi",
      "platform_b": "polymarket",
      "question_a": "Will another country leave OPEC in 2026?",
      "question_b": "Will another country leave OPEC in 2026?",
      "url_a": "https://kalshi.com/markets/KXLEAVEOPEC",
      "url_b": "https://polymarket.com/event/will-another-country-leave-opec-in-2026",
      "market_id_a": "KXLEAVEOPEC-27",
      "market_id_b": "51521497779380154558858664227546451933112892150984250255096573026768867177192",
      "prob_a": 0.365,
      "prob_b": 0.255,
      "stake_a": 28.65,
      "stake_b": 71.35,
      "return_pct": 5.0,
      "settle_date": "2027-01-01",
      "volume_a": 12740.36,
      "volume_b": 104589.77,
      "suspicious": false,
      "suspicion_reasons": []
    },
    {
      "source": "pred-arbitrage",
      "category": "Politics",
      "label": "",
      "platform_a": "kalshi",
      "platform_b": "polymarket",
      "question_a": "Who will be arrested before 2027? \u2014 James Clapper",
      "question_b": "Will James Clapper be arrested before 2027?",
      "url_a": "https://kalshi.com/markets/KXARREST",
      "url_b": "https://polymarket.com/event/who-will-be-arrested-before-2027",
      "market_id_a": "KXARREST-27JAN-JCLA",
      "market_id_b": "74091869724089710488270648353789145218457851880773279383999098316230780589734",
      "prob_a": 0.305,
      "prob_b": 0.195,
      "stake_a": 21.91,
      "stake_b": 78.09,
      "return_pct": 5.0,
      "settle_date": "2027-01-01",
      "volume_a": 52056.02,
      "volume_b": 2645.45,
      "suspicious": false,
      "suspicion_reasons": []
    },
    {
      "source": "pred-arbitrage",
      "category": "Entertainment",
      "label": "",
      "platform_a": "kalshi",
      "platform_b": "polymarket",
      "question_a": "TIME's Person of the Year for 2026? \u2014 Taylor Swift",
      "question_b": "Will Taylor Swift be TIME Person of the Year 2026?",
      "url_a": "https://kalshi.com/markets/KXTIME",
      "url_b": "https://polymarket.com/event/time-person-of-the-year-2026",
      "market_id_a": "KXTIME-26-TS",
      "market_id_b": "4123149736118864694566230758163571517520946389210330950664168360590565059249",
      "prob_a": 0.04,
      "prob_b": 0.15,
      "stake_a": 95.51,
      "stake_b": 4.49,
      "return_pct": 5.0,
      "settle_date": "2027-01-01",
      "volume_a": 13856.38,
      "volume_b": 21.13,
      "suspicious": false,
      "suspicion_reasons": []
    },
    {
      "source": "pred-arbitrage",
      "category": "Elections",
      "label": "",
      "platform_a": "kalshi",
      "platform_b": "polymarket",
      "question_a": "MI-13 Democratic nominee? \u2014 Donavan McKinney",
      "question_b": "Will Donavan McKinney be the Democratic Nominee for MI-13?",
      "url_a": "https://kalshi.com/markets/KXMI13D",
      "url_b": "https://polymarket.com/event/mi-13-democratic-primary-winner",
      "market_id_a": "KXMI13D-26-DMCK",
      "market_id_b": "27221228766846853718706625769824857836480508702996989294458693744073725304682",
      "prob_a": 0.595,
      "prob_b": 0.7,
      "stake_a": 33.52,
      "stake_b": 66.48,
      "return_pct": 4.5,
      "settle_date": "2027-11-03",
      "volume_a": 4171.93,
      "volume_b": 20870.46,
      "suspicious": false,
      "suspicion_reasons": []
    },
    {
      "source": "pred-arbitrage",
      "category": "Politics",
      "label": "",
      "platform_a": "kalshi",
      "platform_b": "polymarket",
      "question_a": "Will Trump recognize Somaliland? \u2014 Before 2027",
      "question_b": "Will Trump recognize Somaliland before 2027?",
      "url_a": "https://kalshi.com/markets/KXRECOGSOMALI",
      "url_b": "https://polymarket.com/event/will-trump-recognize-somaliland-before-2027",
      "market_id_a": "KXRECOGSOMALI-29-27",
      "market_id_b": "102929345572635447239887363328073498574489822201252070158392894695407110289078",
      "prob_a": 0.21,
      "prob_b": 0.109,
      "stake_a": 12.12,
      "stake_b": 87.88,
      "return_pct": 4.1,
      "settle_date": "2027-01-01",
      "volume_a": 6725.2,
      "volume_b": 155426.5,
      "suspicious": false,
      "suspicion_reasons": []
    },
    {
      "source": "pred-arbitrage",
      "category": "Politics",
      "label": "",
      "platform_a": "kalshi",
      "platform_b": "polymarket",
      "question_a": "Who will be arrested before 2027? \u2014 Adam Schiff",
      "question_b": "Will Adam Schiff be arrested before 2027?",
      "url_a": "https://kalshi.com/markets/KXARREST",
      "url_b": "https://polymarket.com/event/who-will-be-arrested-before-2027",
      "market_id_a": "KXARREST-27JAN-ASCH",
      "market_id_b": "89927690970866432638583725236459419388263927903641808909198263362524997727072",
      "prob_a": 0.15,
      "prob_b": 0.05,
      "stake_a": 5.56,
      "stake_b": 94.44,
      "return_pct": 4.0,
      "settle_date": "2027-01-01",
      "volume_a": 44725.22,
      "volume_b": 6572.23,
      "suspicious": false,
      "suspicion_reasons": []
    },
    {
      "source": "pred-arbitrage",
      "category": "Politics",
      "label": "",
      "platform_a": "kalshi",
      "platform_b": "polymarket",
      "question_a": "Who will recognize Palestine before 2027? \u2014 New Zealand",
      "question_b": "Will New Zealand recognize Palestine before 2027?",
      "url_a": "https://kalshi.com/markets/KXRECOGPALESTINE",
      "url_b": "https://polymarket.com/event/which-countries-will-recognize-palestine-before-2027",
      "market_id_a": "KXRECOGPALESTINE-27-NZ",
      "market_id_b": "65570926759968481664272006070778261573308784359007307417544721102990194386816",
      "prob_a": 0.145,
      "prob_b": 0.24,
      "stake_a": 83.98,
      "stake_b": 16.02,
      "return_pct": 3.5,
      "settle_date": "2027-01-01",
      "volume_a": 9441.8,
      "volume_b": 120148.3,
      "suspicious": false,
      "suspicion_reasons": []
    },
    {
      "source": "pred-arbitrage",
      "category": "Elections",
      "label": "",
      "platform_a": "kalshi",
      "platform_b": "polymarket",
      "question_a": "Who will win the 2026 Vancouver mayoral election? \u2014 Pete Fry",
      "question_b": "Will Pete Fry win the 2026 Vancouver mayoral election?",
      "url_a": "https://kalshi.com/markets/KXVANCOUVERMAYOR",
      "url_b": "https://polymarket.com/event/vancouver-mayoral-election-winner",
      "market_id_a": "KXVANCOUVERMAYOR-26OCT17-PFRY",
      "market_id_b": "90282073970311127511205771444554273792281500981661699146096274090779625493121",
      "prob_a": 0.18,
      "prob_b": 0.087,
      "stake_a": 9.59,
      "stake_b": 90.41,
      "return_pct": 3.3,
      "settle_date": "2027-10-17",
      "volume_a": 5626.0,
      "volume_b": 14651.04,
      "suspicious": false,
      "suspicion_reasons": []
    },
    {
      "source": "pred-arbitrage",
      "category": "Elections",
      "label": "",
      "platform_a": "kalshi",
      "platform_b": "polymarket",
      "question_a": "Who will advance from the CA-22 primary? \u2014 Chris Mathys",
      "question_b": "Will Chris Mathys advance from the CA-22 Primary?",
      "url_a": "https://kalshi.com/markets/KXCA22PRIMARY",
      "url_b": "https://polymarket.com/event/ca-22-primary-winners",
      "market_id_a": "KXCA22PRIMARY-26-CMAT",
      "market_id_b": "5776983690450810166348390386241244875928868583471779309964316179469216646481",
      "prob_a": 0.018,
      "prob_b": 0.194,
      "stake_a": 97.82,
      "stake_b": 2.18,
      "return_pct": 11.6,
      "settle_date": "2026-11-03",
      "volume_a": 813.0,
      "volume_b": 588.73,
      "suspicious": true,
      "suspicion_reasons": [
        "wide_spread_b"
      ]
    },
    {
      "source": "pred-arbitrage",
      "category": "Entertainment",
      "label": "",
      "platform_a": "kalshi",
      "platform_b": "polymarket",
      "question_a": "Who will win Chopped Castaways: Season 1? \u2014 James Peck",
      "question_b": "Will James Peck win Chopped Castaways Season 1?",
      "url_a": "https://kalshi.com/markets/KXCHOPPEDCASTAWAYS",
      "url_b": "https://polymarket.com/event/who-will-win-chopped-castaways",
      "market_id_a": "KXCHOPPEDCASTAWAYS-26DEC31-JAM",
      "market_id_b": "65897326300830939126472993878733576121136544817916286512629178390203006282736",
      "prob_a": 0.01,
      "prob_b": 0.182,
      "stake_a": 98.79,
      "stake_b": 1.21,
      "return_pct": 11.2,
      "settle_date": "2027-01-07",
      "volume_a": 3952.52,
      "volume_b": 94.1,
      "suspicious": true,
      "suspicion_reasons": [
        "one_sided_a",
        "wide_spread_b"
      ]
    },
    {
      "source": "pred-arbitrage",
      "category": "Entertainment",
      "label": "",
      "platform_a": "kalshi",
      "platform_b": "polymarket",
      "question_a": "Who will win Chopped Castaways: Season 1? \u2014 Carrie Baird",
      "question_b": "Will Carrie Baird win Chopped Castaways Season 1?",
      "url_a": "https://kalshi.com/markets/KXCHOPPEDCASTAWAYS",
      "url_b": "https://polymarket.com/event/who-will-win-chopped-castaways",
      "market_id_a": "KXCHOPPEDCASTAWAYS-26DEC31-CAR",
      "market_id_b": "17880391068734413994424969693750950450882248702336181473442474274652275014746",
      "prob_a": 0.01,
      "prob_b": 0.175,
      "stake_a": 98.8,
      "stake_b": 1.2,
      "return_pct": 10.5,
      "settle_date": "2027-01-07",
      "volume_a": 4174.72,
      "volume_b": 94.1,
      "suspicious": true,
      "suspicion_reasons": [
        "one_sided_a",
        "wide_spread_b"
      ]
    },
    {
      "source": "pred-arbitrage",
      "category": "Entertainment",
      "label": "",
      "platform_a": "kalshi",
      "platform_b": "polymarket",
      "question_a": "Who will win Chopped Castaways: Season 1? \u2014 Logan Sandoval",
      "question_b": "Will Logan Sandoval win Chopped Castaways Season 1?",
      "url_a": "https://kalshi.com/markets/KXCHOPPEDCASTAWAYS",
      "url_b": "https://polymarket.com/event/who-will-win-chopped-castaways",
      "market_id_a": "KXCHOPPEDCASTAWAYS-26DEC31-LOG",
      "market_id_b": "47725282969396099461136632712569906984945046787297565754377108058366742147015",
      "prob_a": 0.01,
      "prob_b": 0.155,
      "stake_a": 98.83,
      "stake_b": 1.17,
      "return_pct": 8.5,
      "settle_date": "2027-01-07",
      "volume_a": 3842.42,
      "volume_b": 103.1,
      "suspicious": true,
      "suspicion_reasons": [
        "one_sided_a"
      ]
    },
    {
      "source": "pred-arbitrage",
      "category": "Politics",
      "label": "",
      "platform_a": "kalshi",
      "platform_b": "polymarket",
      "question_a": "Who will recognize Palestine before 2027? \u2014 Greece",
      "question_b": "Will Greece recognize Palestine before 2027?",
      "url_a": "https://kalshi.com/markets/KXRECOGPALESTINE",
      "url_b": "https://polymarket.com/event/which-countries-will-recognize-palestine-before-2027",
      "market_id_a": "KXRECOGPALESTINE-27-GRE",
      "market_id_b": "9568640529628232620171982414821256284849638329588081306176647962997142501307",
      "prob_a": 0.1005,
      "prob_b": 0.242,
      "stake_a": 88.29,
      "stake_b": 11.71,
      "return_pct": 8.15,
      "settle_date": "2027-01-01",
      "volume_a": 7027.0,
      "volume_b": 45956.0,
      "suspicious": true,
      "suspicion_reasons": [
        "wide_spread_b"
      ]
    },
    {
      "source": "pred-arbitrage",
      "category": "Elections",
      "label": "",
      "platform_a": "kalshi",
      "platform_b": "polymarket",
      "question_a": "CA-14 special election winner \u2014 Victor Aguilar Jr.",
      "question_b": "Will Victor Aguilar Jr. win the CA-14 special election?",
      "url_a": "https://kalshi.com/markets/KXCA14SWINNER",
      "url_b": "https://polymarket.com/event/ca-14-special-election-winner",
      "market_id_a": "KXCA14SWINNER-26-VAGU",
      "market_id_b": "109174591737084143263286220074318085920277392845795106244192747561321532781576",
      "prob_a": 0.01,
      "prob_b": 0.123,
      "stake_a": 98.87,
      "stake_b": 1.13,
      "return_pct": 5.3,
      "settle_date": "2027-11-03",
      "volume_a": 75.0,
      "volume_b": 219.52,
      "suspicious": true,
      "suspicion_reasons": [
        "one_sided_a",
        "thin_depth_b"
      ]
    },
    {
      "source": "pred-arbitrage",
      "category": "Entertainment",
      "label": "",
      "platform_a": "kalshi",
      "platform_b": "polymarket",
      "question_a": "Who will win Chopped Castaways: Season 1? \u2014 Ara Zada",
      "question_b": "Will Ara Zada win Chopped Castaways Season 1?",
      "url_a": "https://kalshi.com/markets/KXCHOPPEDCASTAWAYS",
      "url_b": "https://polymarket.com/event/who-will-win-chopped-castaways",
      "market_id_a": "KXCHOPPEDCASTAWAYS-26DEC31-ARA",
      "market_id_b": "15179162995150274575824932945827733080078171865422030199399313325723906644764",
      "prob_a": 0.02,
      "prob_b": 0.128,
      "stake_a": 97.76,
      "stake_b": 2.24,
      "return_pct": 4.8,
      "settle_date": "2027-01-07",
      "volume_a": 8046.27,
      "volume_b": 123.35,
      "suspicious": true,
      "suspicion_reasons": [
        "one_sided_a"
      ]
    },
    {
      "source": "pred-arbitrage",
      "category": "Entertainment",
      "label": "",
      "platform_a": "kalshi",
      "platform_b": "polymarket",
      "question_a": "Who will be People's Sexiest Man Alive in 2026? \u2014 Ryan Gosling",
      "question_b": "Will Ryan Gosling be named People's Sexiest Man Alive in 2026?",
      "url_a": "https://kalshi.com/markets/KXSEXYMAN",
      "url_b": "https://polymarket.com/event/peoples-sexiest-man-alive-2026",
      "market_id_a": "KXSEXYMAN-26-RYA",
      "market_id_b": "74138026058396993008620723026811617321717254031993052273057397079964254793298",
      "prob_a": 0.055,
      "prob_b": 0.16,
      "stake_a": 93.85,
      "stake_b": 6.15,
      "return_pct": 4.5,
      "settle_date": "2027-01-01",
      "volume_a": 1166.79,
      "volume_b": 337.65,
      "suspicious": true,
      "suspicion_reasons": [
        "thin_depth_a"
      ]
    },
    {
      "source": "pred-arbitrage",
      "category": "Entertainment",
      "label": "",
      "platform_a": "kalshi",
      "platform_b": "polymarket",
      "question_a": "Who will be People's Sexiest Man Alive in 2026? \u2014 Timoth\u00e9e Chalamet",
      "question_b": "Will Timoth\u00e9e Chalamet be named People's Sexiest Man Alive in 2026?",
      "url_a": "https://kalshi.com/markets/KXSEXYMAN",
      "url_b": "https://polymarket.com/event/peoples-sexiest-man-alive-2026",
      "market_id_a": "KXSEXYMAN-26-TIM",
      "market_id_b": "5748755663394163980111799080810479668203966805541715418860023064880106813587",
      "prob_a": 0.055,
      "prob_b": 0.16,
      "stake_a": 93.85,
      "stake_b": 6.15,
      "return_pct": 4.5,
      "settle_date": "2027-01-01",
      "volume_a": 2877.97,
      "volume_b": 1832.88,
      "suspicious": true,
      "suspicion_reasons": [
        "thin_depth_b"
      ]
    },
    {
      "source": "pred-arbitrage",
      "category": "Elections",
      "label": "",
      "platform_a": "kalshi",
      "platform_b": "polymarket",
      "question_a": "Who will be the next new Prime Minister of Romania? \u2014 Alexandru Nazare",
      "question_b": "Will Alexandru Nazare be the next Prime Minister of Romania?",
      "url_a": "https://kalshi.com/markets/KXNEXTROMANIAPM",
      "url_b": "https://polymarket.com/event/next-prime-minister-of-romania-732",
      "market_id_a": "KXNEXTROMANIAPM-45JAN01-ANAZ",
      "market_id_b": "53608778687946526087931275341829969687544820721765237719012884473441162777718",
      "prob_a": 0.145,
      "prob_b": 0.245,
      "stake_a": 83.89,
      "stake_b": 16.11,
      "return_pct": 4.0,
      "settle_date": "2045-01-01",
      "volume_a": 551.0,
      "volume_b": 54848.85,
      "suspicious": true,
      "suspicion_reasons": [
        "thin_depth_a",
        "wide_spread_b"
      ]
    },
    {
      "source": "pred-arbitrage",
      "category": "Entertainment",
      "label": "",
      "platform_a": "kalshi",
      "platform_b": "polymarket",
      "question_a": "Who will win Top Chef Season 23? \u2014 Sherry Cardoso",
      "question_b": "Will Sherry Cardoso win Top Chef Season 23?",
      "url_a": "https://kalshi.com/markets/KXTOPCHEF",
      "url_b": "https://polymarket.com/event/who-will-win-top-chef-season-23",
      "market_id_a": "KXTOPCHEF-26DEC31-SHER",
      "market_id_b": "63562924338850682963805565242660808997719400293270081663492095629864081683987",
      "prob_a": 0.1,
      "prob_b": 0.006,
      "stake_a": 0.66,
      "stake_b": 99.34,
      "return_pct": 3.4,
      "settle_date": "2027-01-07",
      "volume_a": 43628.73,
      "volume_b": 2729.53,
      "suspicious": true,
      "suspicion_reasons": [
        "one_sided_a"
      ]
    }
  ]
}
